pyramid_auto_env
