Metadata-Version: 2.1
Name: pyramid-auto-env
Version: 0.1.0
Summary: Pyramid Autoenv
Home-page: https://github.com/marcelomoraes28/pyramid-auto-env
Author: Marcelo Moraes
Author-email: marcelomoraesjr28@gmail.com
License: UNKNOWN
Keywords: autoenv pyramid
Platform: UNKNOWN
Classifier: Development Status :: 3 - Alpha
Classifier: Programming Language :: Python
Classifier: License :: OSI Approved :: MIT License
Classifier: Topic :: Software Development :: Libraries :: Python Modules
Classifier: Programming Language :: Python :: 2.7
Classifier: Programming Language :: Python :: 3.5
Classifier: Programming Language :: Python :: 3.6
Provides-Extra: ci
Provides-Extra: test
